forecapp_api/Procfile
forecapp_api/app/__init__.py
forecapp_api/app/config.py
forecapp_api/app/events.py
forecapp_api/gunicorn.conf.py
forecapp_api/logs/.keep
forecapp_api/main.py
forecapp_api-0.1.3.dist-info/METADATA
forecapp_api-0.1.3.dist-info/WHEEL
forecapp_api-0.1.3.dist-info/RECORD
