Metadata-Version: 2.1
Name: forecapp-api
Version: 0.1.3
Summary: 
Author: Richard
Author-email: richard@stromer.org
Requires-Python: >=3.10,<3.11
Classifier: Programming Language :: Python :: 3
Classifier: Programming Language :: Python :: 3.10
Requires-Dist: fastapi (==0.88.0)
Requires-Dist: fastapi-camelcase (==1.0.5)
Requires-Dist: gunicorn (==20.1.0)
Requires-Dist: neuralprophet (==0.6.0.rc1)
Requires-Dist: sentry-sdk[fastapi] (==1.10.1)
Requires-Dist: uvicorn[standard] (==0.20.0)
